pypapple/__init__.py
pypapple/__main__.py
pypapple/p_object.py
pypapple/util.py
pypapple-0.0.2.dist-info/METADATA
pypapple-0.0.2.dist-info/WHEEL
pypapple-0.0.2.dist-info/entry_points.txt
pypapple-0.0.2.dist-info/top_level.txt
pypapple-0.0.2.dist-info/RECORD
