Metadata-Version: 2.4
Name: pypapple
Version: 0.0.2
Summary: A Python implementation of the Iwa interpreter for the Pineapple programming language
Home-page: https://github.com/Robert-DeForrest-Reynolds/PyPapple
Author: Robert Lawrence DeForrest Reynolds
License-Expression: MIT
Project-URL: Homepage, https://github.com/Robert-DeForrest-Reynolds/PyPapple
Project-URL: Repository, https://github.com/Robert-DeForrest-Reynolds/PyPapple
Requires-Python: >=3
